nessus_aggregator/__init__.py
nessus_aggregator/config.py
nessus_aggregator/nessus_aggregator.py
nessus_aggregator-0.2.3.dist-info/METADATA
nessus_aggregator-0.2.3.dist-info/WHEEL
nessus_aggregator-0.2.3.dist-info/entry_points.txt
nessus_aggregator-0.2.3.dist-info/top_level.txt
nessus_aggregator-0.2.3.dist-info/RECORD
