Metadata-Version: 2.1
Name: nessus-aggregator
Version: 0.2.3
Summary: Aggregate Nessus vulnerability scan results into consolidated Excel reports.
Home-page: https://github.com/admiralsyn-ackbar/nessus-aggregator
Author: Admiral SYN-ACKbar
Author-email: admiral@admiralsyn-ackbar.com
Classifier: Programming Language :: Python :: 3
Classifier: License :: OSI Approved :: GNU General Public License v3 (GPLv3)
Classifier: Operating System :: POSIX :: Linux
Requires-Python: >=3.7
Requires-Dist: pandas>=1.0.0
Requires-Dist: requests>=2.25.0
Requires-Dist: urllib3>=1.26.0
Requires-Dist: nessus-file-reader>=0.1.0
Requires-Dist: xlsxwriter>=3.0.0
